LICENSE.txt
MANIFEST.in
README.md
setup.cfg
setup.py
SpirentSLC/Execution.py
SpirentSLC/SLC.py
SpirentSLC/__init__.py
SpirentSLC/builtin_sessions.py
SpirentSLC/config.py
SpirentSLC/exception.py
SpirentSLC/identity.py
SpirentSLC/project.py
SpirentSLC/python_name.py
SpirentSLC/resources.py
SpirentSLC/session_profile.py
SpirentSLC/session_response.py
SpirentSLC/test_case.py
SpirentSLC/topology.py
SpirentSLC.egg-info/PKG-INFO
SpirentSLC.egg-info/SOURCES.txt
SpirentSLC.egg-info/dependency_links.txt
SpirentSLC.egg-info/requires.txt
SpirentSLC.egg-info/top_level.txt
SpirentSLC/internal/ExecutionProtocol.proto
SpirentSLC/internal/ExecutionProtocol_pb2.py
SpirentSLC/internal/__init__.py
SpirentSLC/internal/cache.py
SpirentSLC/internal/protocol.py
SpirentSLC/internal/response_storage.py
SpirentSLC/yaml_execution/__init__.py
SpirentSLC/yaml_execution/errors.py
SpirentSLC/yaml_execution/matcher.py
SpirentSLC/yaml_execution/operations.py
SpirentSLC/yaml_execution/utils.py
examples/UAC.py
examples/example.py
examples/example1.py
examples/example2.py
examples/example3.py
examples/itars/NativePyLib.itar
examples/itars/my_project.itar
examples/itars/response_map_test_prj.itar
resources/__init__.py
resources/paths.py